LICENSE.txt
MANIFEST.in
README.md
setup.py
cjvt_conversion_utils.egg-info/PKG-INFO
cjvt_conversion_utils.egg-info/SOURCES.txt
cjvt_conversion_utils.egg-info/dependency_links.txt
cjvt_conversion_utils.egg-info/requires.txt
cjvt_conversion_utils.egg-info/top_level.txt
cjvt_conversion_utils.egg-info/zip-safe
conversion_utils/__init__.py
conversion_utils/conllu_to_tei.py
conversion_utils/jos_msds_and_properties.py
conversion_utils/tei_to_dictionary.py
conversion_utils/translate_conllu_jos.py
conversion_utils/utils.py
conversion_utils/resources/__init__.py
conversion_utils/resources/dict.xml
conversion_utils/resources/jos_specifications.pickle
conversion_utils/resources/structure_conversions.csv
conversion_utils/tests/__init__.py
conversion_utils/tests/test_jos_msd_to_properties.py
conversion_utils/tests/test_jos_properties_to_msd.py
conversion_utils/tests/test_jos_translate_msd.py
conversion_utils/tests/test_jos_translate_properties.py