Metadata-Version: 2.1
Name: cjvt-conversion-utils
Version: 0.2
Summary: CJVT conversion utilities
Home-page: https://gitea.cjvt.si/generic/conversion_utils
Author: CJVT
Author-email: pypi@cjvt.si
License: MIT
Platform: UNKNOWN
License-File: LICENSE.txt
